[
    {
        "id": "1",
        "nombre": "Alta Verapaz"
    },
    {
        "id": "2",
        "nombre": "Baja Verapaz"
    },
    {
        "id": "3",
        "nombre": "Chimaltenango"
    },
    {
        "id": "4",
        "nombre": "Chiquimula"
    },
    {
        "id": "5",
        "nombre": "El Progreso"
    },
    {
        "id": "6",
        "nombre": "Escuintla"
    },
    {
        "id": "7",
        "nombre": "Guatemala"
    },
    {
        "id": "8",
        "nombre": "Huehuetenango"
    },
    {
        "id": "9",
        "nombre": "Izabal"
    },
    {
        "id": "10",
        "nombre": "Jalapa"
    },
    {
        "id": "11",
        "nombre": "Jutiapa"
    },
    {
        "id": "12",
        "nombre": "Petén"
    },
    {
        "id": "13",
        "nombre": "Quetzaltenango"
    },
    {
        "id": "14",
        "nombre": "Quiché"
    },
    {
        "id": "15",
        "nombre": "Retalhuleu"
    },
    {
        "id": "16",
        "nombre": "Sacatepéquez"
    },
    {
        "id": "17",
        "nombre": "San Marcos"
    },
    {
        "id": "18",
        "nombre": "Santa Rosa"
    },
    {
        "id": "19",
        "nombre": "Sololá"
    },
    {
        "id": "20",
        "nombre": "Suchitepéquez"
    },
    {
        "id": "21",
        "nombre": "Totonicapán"
    },
    {
        "id": "22",
        "nombre": "Zacapa"
    }
]
